sf_streamlit_utils/__init__.py
sf_streamlit_utils/cache.py
sf_streamlit_utils/config.py
sf_streamlit_utils/connection.py
sf_streamlit_utils/helpers.py
sf_streamlit_utils/logging_utils.py
flakestream-0.1.12.dist-info/METADATA
flakestream-0.1.12.dist-info/WHEEL
flakestream-0.1.12.dist-info/top_level.txt
flakestream-0.1.12.dist-info/RECORD
