Metadata-Version: 2.4
Name: flakestream
Version: 0.1.12
Summary: Streamlit-focused utilities for Snowflake: standardized connections, resilient caching, helpers, and optional schema browser.
Author-email: Will Sheehan <snowflake.utilities@gmail.com>
Requires-Python: >=3.9
Requires-Dist: streamlit>=1.29
Requires-Dist: snowflake-connector-python>=3.0
Requires-Dist: snowflake-snowpark-python>=1.10
Requires-Dist: pandas>=1.5
Requires-Dist: typing-extensions>=4.6
Provides-Extra: dev
Requires-Dist: pytest>=7.0; extra == "dev"
Requires-Dist: pytest-mock>=3.10; extra == "dev"
Requires-Dist: ruff>=0.4; extra == "dev"
Requires-Dist: black>=24.1.0; extra == "dev"
Requires-Dist: mypy>=1.8; extra == "dev"
